b1u3calculator/__init__.py
b1u3calculator/ast.py
b1u3calculator/evaluator.py
b1u3calculator/lexer.py
b1u3calculator/main.py
b1u3calculator/obj.py
b1u3calculator/parser.py
b1u3calculator/repl.py
b1u3calculator/token.py
B1u3Calculator-1.0.1.dist-info/LICENSE.txt
B1u3Calculator-1.0.1.dist-info/METADATA
B1u3Calculator-1.0.1.dist-info/WHEEL
B1u3Calculator-1.0.1.dist-info/entry_points.txt
B1u3Calculator-1.0.1.dist-info/top_level.txt
B1u3Calculator-1.0.1.dist-info/RECORD
