Metadata-Version: 2.1
Name: B1u3Calculator
Version: 1.0.1
Summary: kyuvie's calculator.
Home-page: https://github.com/kyuvie/Calculator
Author: kyuvie
Author-email: alchemy.lapidis.philosophorum.13@gmail.com
License: UNKNOWN
Keywords: calculator pratts language
Platform: UNKNOWN
Classifier: Programming Language :: Python :: 3
Classifier: Programming Language :: Python :: 3.8
Requires-Python: >=3.5, <4
Provides-Extra: dev
Requires-Dist: check-manifest ; extra == 'dev'
Provides-Extra: test
Requires-Dist: coverage ; extra == 'test'
